myevae/__init__.py
myevae/__main__.py
myevae/buildnetwork.py
myevae/coxphloss.py
myevae/dataset.py
myevae/estimator.py
myevae/kldivergence.py
myevae/nn.py
myevae/param_grid.py
myevae/params.py
myevae/pipelinetools.py
myevae/plotshap.py
myevae/preprocess.py
myevae/score.py
myevae/shap.py
myevae/train.py
myevae/type_prefixes.py
myevae/data/ensembl_ref.csv
myevae-0.0.2.dist-info/licenses/LICENSE
myevae-0.0.2.dist-info/METADATA
myevae-0.0.2.dist-info/WHEEL
myevae-0.0.2.dist-info/entry_points.txt
myevae-0.0.2.dist-info/top_level.txt
myevae-0.0.2.dist-info/RECORD
