Metadata-Version: 2.4
Name: myevae
Version: 0.0.2
Summary: MyeVAE: a multi-modal variational autoencoder for risk profiling of newly diagnosed multiple myeloma
Author: Chang Jia Geng, Jianbin Chen, Guo-Liang Chew, Wee Joo Chng
Maintainer-email: Chang Jia Geng <jiageng1997@gmail.com>
License-Expression: MIT
Project-URL: Homepage, https://github.com/JiaGengChang/myevae
Project-URL: Software-Repo, https://github.com/JiaGengChang/myevae.git
Project-URL: Publication-Repo, https://github.com/JiaGengChang/myevae-paper.git
Project-URL: Issues, https://github.com/JiaGengChang/myevae/issues
Project-URL: Example-Inputs, https://myevae.s3.us-east-1.amazonaws.com/example_inputs.tar.gz
Project-URL: Example-Outputs, https://myevae.s3.us-east-1.amazonaws.com/example_outputs.tar.gz
Keywords: multiomics,myeloma,VAE,variational autoencoder,omics integration,command line tool
Classifier: Development Status :: 4 - Beta
Classifier: Operating System :: POSIX :: Linux
Classifier: Programming Language :: Python :: 3
Classifier: Programming Language :: Python :: 3.9
Classifier: Programming Language :: Python :: 3.10
Classifier: Programming Language :: Python :: 3.11
Classifier: Programming Language :: Python :: 3.12
Classifier: Programming Language :: Python :: 3.13
Classifier: Intended Audience :: Developers
Classifier: Intended Audience :: Science/Research
Classifier: Intended Audience :: Healthcare Industry
Classifier: Topic :: Scientific/Engineering :: Bio-Informatics
Classifier: Topic :: Scientific/Engineering :: Artificial Intelligence
Requires-Python: >=3.9
License-File: LICENSE
Requires-Dist: torch>=1.9.0
Requires-Dist: scikit-survival>=0.23.0
Requires-Dist: scikit-learn>=0.24.1
Requires-Dist: importlib_resources
Requires-Dist: matplotlib
Requires-Dist: dask[distributed]
Requires-Dist: shap-0.47.3.dev8-offline-fork-for-myevae==0.0.1
Dynamic: license-file
